{
    "name": "RooRay's Settings",
    "description": "A preset that includes a fairly minimalistic interface whilst still being feature-rich.",
    "type": "settings",
    "version": "1.0.0",
    "author": "RooRay",
    "icon_url": "https://i.imgur.com/pPGz0zv.png",
    "screenshot_url": "https://i.imgur.com/qlvNgaI.png",
    "settings": {
        "searchBar": "true",
        "toastDisplayTime": "2500",
        "weeknumber": "false",
        "notesPinned": "false",
        "offlineMode": "false",
        "hourHand": "true",
        "refresh": "false",
        "greeting": "true",
        "tempformat": "celsius",
        "birthday": "",
        "windspeed": "true",
        "dayofweek": "true",
        "backgroundVideoLoop": "true",
        "fontweight": "400",
        "location": "",
        "fontstyle": "normal",
        "backgroundFilter": "none",
        "datezero": "true",
        "windDirection": "false",
        "fontGoogle": "false",
        "weatherEnabled": "false",
        "brightness": "90",
        "copyButton": "false",
        "ddgProxy": "true",
        "favouriteQuoteEnabled": "false",
        "apiQuality": "high",
        "backgroundFilterAmount": "0",
        "showlocation": "true",
        "authorLink": "true",
        "background": "true",
        "animations": "true",
        "defaultGreetingMessage": "true",
        "events": "true",
        "greetingName": "User",
        "favouriteEnabled": "true",
        "customBackgroundColour": "{\"angle\":\"180\",\"gradient\":[{\"colour\":\"#ffb032\",\"stop\":0}],\"type\":\"linear\"}",
        "humidity": "true",
        "weatherdescription": "false",
        "shortFormat": "dots",
        "quoteType": "api",
        "backgroundType": "api",
        "backgroundAPI": "pexels",
        "customBackground": "",
        "notes": "",
        "cloudiness": "false",
        "time": "true",
        "order": "[\"greeting\",\"time\",\"quote\",\"date\",\"quicklinks\",\"message\"]",
        "tabName": "New Tab",
        "zero": "true",
        "birthdayenabled": "true",
        "currentBackground": "{}",
        "font": "",
        "timezone": "auto",
        "backgroundVideoMute": "true",
        "autocomplete": "true",
        "view": "true",
        "dateFormat": "DMY",
        "timeType": "digital",
        "atmosphericpressure": "false",
        "date": "true",
        "maxtemp": "true",
        "quicklinksddgProxy": "true",
        "photoInformation": "true",
        "theme": "auto",
        "photoMap": "true",
        "searchDropdown": "true",
        "quicklinksenabled": "false",
        "mintemp": "true",
        "quicklinks": "[]",
        "birthdayage": "true",
        "welcomeImage": "{\"style\":\"\",\"url\":\"./offline-images/6.webp\",\"currentAPI\":\"\",\"photoInfo\":{\"offline\":true,\"credit\":\"Frank Mckenna\"}}",
        "currentQuote": "{\"quote\":\"\\\"You are the only one who can limit your greatness\\\"\",\"author\":\"Unknown\",\"authorlink\":null,\"quoteLanguage\":\"English\"}",
        "blur": "5",
        "quicklinkstooltip": "true",
        "visibility": "false",
        "autocompleteProvider": "google",
        "searchEngine": "google",
        "quote": "false",
        "notesEnabled": "true",
        "minuteHand": "true",
        "bgtransition": "true",
        "tweetButton": "false",
        "timeformat": "twelvehour"
    }
}