{
  "name": "Unsplash Photos",
  "display_name": "Unsplash Photos",
  "type": "photos",
  "description": "Beautiful photos from Unsplash collections. Dynamically fetched photos with optional custom collections. Internet connection required, with offline caching support.",
  "version": "1.0.0",
  "author": "The Mue Authors",
  "icon_url": "https://avatars.githubusercontent.com/u/9951955?s=200&v=4",
  "screenshot_url": "https://avatars.githubusercontent.com/u/9951955?s=200&v=4",

  "api_enabled": true,
  "api_provider": "unsplash",
  "requires_api_key": false,

  "photos": [],

  "settings_schema": [
    {
      "key": "collections",
      "type": "text",
      "label": "Collection IDs",
      "placeholder": "e.g. 123456, 654321",
      "default": "",
      "required": false,
      "help_text": "Optional: Comma-separated collection IDs to fetch photos from"
    }
  ]
}
